kwargify.py
setup.py
kwargify.egg-info/PKG-INFO
kwargify.egg-info/SOURCES.txt
kwargify.egg-info/dependency_links.txt
kwargify.egg-info/pbr.json
kwargify.egg-info/top_level.txt