Metadata-Version: 1.1
Name: kwargify
Version: 2.1.0
Summary: Python function kwargifier
Home-page: https://github.com/mfalesni/python-kwargify
Author: Milan Falešník
Author-email: milan@falesnik.net
License: GPLv2
Keywords: kwargs
Platform: UNKNOWN
Classifier: Topic :: Utilities
Classifier: License :: OSI Approved :: GNU General Public License v2 (GPLv2)
